component_include_tags/__init__.py
component_include_tags/apps.py
component_include_tags/tests.py
component_include_tags/migrations/__init__.py
component_include_tags/templatetags/__init__.py
component_include_tags/templatetags/components.py
django_component_include_tags-0.0.3.dist-info/LICENCE
django_component_include_tags-0.0.3.dist-info/METADATA
django_component_include_tags-0.0.3.dist-info/WHEEL
django_component_include_tags-0.0.3.dist-info/top_level.txt
django_component_include_tags-0.0.3.dist-info/RECORD
