Metadata-Version: 2.1
Name: django-component-include-tags
Version: 0.0.3
Summary: Component template tags for Django
Project-URL: Homepage, https://github.com/redmondscales/django-component-include-tags
Project-URL: Bug Tracker, https://github.com/redmondscales/django-component-include-tags/issues
Classifier: Programming Language :: Python :: 3
Classifier: License :: OSI Approved :: MIT License
Classifier: Operating System :: OS Independent
Requires-Python: >=3.7
License-File: LICENCE
